dlc_gui/__init__.py
dlc_gui/__main__.py
dlc_gui/data.py
dlc_gui/gui.py
dlc_gui/util.py
dlc_gui-0.6.1.dist-info/LICENSE
dlc_gui-0.6.1.dist-info/WHEEL
dlc_gui-0.6.1.dist-info/METADATA
dlc_gui-0.6.1.dist-info/RECORD
