Metadata-Version: 2.1
Name: dlc-gui
Version: 0.6.1
Summary: Labeling GUI for DeepLabCut
Home-page: UNKNOWN
License: LGPL-3.0+
Author: d_
Author-email: UnicodeAlt255@gmail.com
Requires-Python: >=3.6,<4.0
Classifier: License :: OSI Approved :: GNU Lesser General Public License v3 or later (LGPLv3+)
Classifier: Programming Language :: Python :: 3
Classifier: Programming Language :: Python :: 3.6
Classifier: Programming Language :: Python :: 3.7
Requires-Dist: PySide2 (==5.11.2)
Requires-Dist: numpy (>=1.0.0,<2.0.0)
Requires-Dist: pandas (>=0.24.0,<0.25.0)
Requires-Dist: ruamel.yaml (>=0.15,<0.16)
Requires-Dist: tables (>=3.4,<4.0)
